medstat/__init__.py
medstat/medstat.py
medstat-1.0.2.dist-info/LICENSE
medstat-1.0.2.dist-info/METADATA
medstat-1.0.2.dist-info/WHEEL
medstat-1.0.2.dist-info/top_level.txt
medstat-1.0.2.dist-info/RECORD
