Metadata-Version: 2.1
Name: medstat
Version: 1.0.2
Summary: Basic hypothesis testing made simple
Home-page: https://github.com/monferrand/medstat
Author: Pierre Monferrand
License: MIT license
Keywords: medstat
Platform: UNKNOWN
Classifier: Development Status :: 5 - Production/Stable
Classifier: Intended Audience :: Developers
Classifier: License :: OSI Approved :: MIT License
Classifier: Natural Language :: English
Classifier: Programming Language :: Python :: 3
Classifier: Programming Language :: Python :: 3.6
Classifier: Programming Language :: Python :: 3.7
Classifier: Programming Language :: Python :: 3.8
Requires-Python: >=3.6
Requires-Dist: pandas
Requires-Dist: scipy
